topsis/102017142.py
topsis/__init__.py
topsis_Shantam_102017142-1.0.0.dist-info/LICENSE.txt
topsis_Shantam_102017142-1.0.0.dist-info/METADATA
topsis_Shantam_102017142-1.0.0.dist-info/WHEEL
topsis_Shantam_102017142-1.0.0.dist-info/top_level.txt
topsis_Shantam_102017142-1.0.0.dist-info/RECORD
